application/AppRunner.py
application/PFApplication.py
application/PFApplicationTest.py
application/PFSktime.py
application/WindowComparator.py
application/__init__.py
application/crossvalidation.py
core/AppContext.py
core/ExperimentRunner.py
core/FileReader.py
core/PFResult.py
core/TreeStatCollector.py
core/__init__.py
dataStructures/ListDataset.py
dataStructures/__init__.py
distance/DistanceMeasure.py
distance/ERP.py
distance/EuclieanDistance.py
distance/MSM.py
distance/TWE.py
distance/__init__.py
distance/lcss.py
trees/Node.py
trees/ProximityForest.py
trees/ProximityTree.py
trees/Splitter.py
trees/__init__.py
Pforests_dtw-1.1.dist-info/METADATA
Pforests_dtw-1.1.dist-info/WHEEL
Pforests_dtw-1.1.dist-info/top_level.txt
Pforests_dtw-1.1.dist-info/RECORD
