Metadata-Version: 2.1
Name: Pforests-dtw
Version: 1.1
Summary: Proximity Forest Classifier using DTW distance measure
Home-page: https://github.com/moradisten/ProximityForests-python
Author: Moradisten
Author-email: moradabaz@gmail.com
License: UNKNOWN
Keywords: time series classification
Platform: UNKNOWN
Requires-Python: >=3.6
Requires-Dist: numpy
Requires-Dist: dtaidistance
Requires-Dist: pytest
Requires-Dist: scipy
